[
  {
    "Plan": {
      "Partial Mode": "Simple",
      "Startup Cost": 308661.16,
      "Plans": [
        {
          "Filter": "((year >= 2000) AND (year <= 2017))",
          "Startup Cost": 0,
          "Node Type": "Seq Scan",
          "Plan Rows": 3279362,
          "Relation Name": "publication",
          "Alias": "publication",
          "Parallel Aware": false,
          "Parent Relationship": "Outer",
          "Plan Width": 8,
          "Total Cost": 292264.35
        }
      ],
      "Node Type": "Aggregate",
      "Strategy": "Hashed",
      "Plan Rows": 7,
      "Parallel Aware": false,
      "Group Key": [
        "type"
      ],
      "Plan Width": 16,
      "Total Cost": 308661.23
    }
  }
]